{"trial_id": "002", "hyperparameters": {"space": [{"class_name": "Int", "config": {"name": "num_neurons", "default": null, "conditions": [], "min_value": 1, "max_value": 256, "step": 1, "sampling": "linear"}}, {"class_name": "Int", "config": {"name": "num_layers", "default": null, "conditions": [], "min_value": 1, "max_value": 16, "step": 1, "sampling": "linear"}}, {"class_name": "Boolean", "config": {"name": "dropoutT/F", "default": false, "conditions": []}}], "values": {"num_neurons": 238, "num_layers": 8, "dropoutT/F": false}}, "metrics": {"metrics": {"loss": {"direction": "min", "observations": [{"value": [0.014198419637978077], "step": 38}]}, "val_loss": {"direction": "min", "observations": [{"value": [0.011507810093462467], "step": 38}]}}}, "score": 0.011507810093462467, "best_step": 38, "status": "COMPLETED", "message": null}